{
    "ha5":{
    "text":" | 縖 | ",
    "romazi":"",
    "hanzis":"縖",
    "hanzit":"",
    "variant":"",
    "etymology":"",
    "partOfSpeech":"",
    "types":"",
    "definition":[""],
    "example":[""],
    "note":"",
    "update":""
  },
"hax-thi2":{
    "text":" | 合体 | ",
    "romazi":"",
    "hanzis":"合体",
    "hanzit":"",
    "variant":"",
    "etymology":"",
    "partOfSpeech":"",
    "types":"",
    "definition":[""],
    "example":[""],
    "note":"",
    "update":""
  },
"ham7-hai7":{
    "text":" | 陷害 | ",
    "romazi":"",
    "hanzis":"陷害",
    "hanzit":"",
    "variant":"",
    "etymology":"",
    "partOfSpeech":"",
    "types":"",
    "definition":[""],
    "example":[""],
    "note":"",
    "update":""
  },
"hap":{
    "text":" | 合 | ",
    "romazi":"",
    "hanzis":"合",
    "hanzit":"",
    "variant":"",
    "etymology":"",
    "partOfSpeech":"",
    "types":"",
    "definition":[""],
    "example":[""],
    "note":"",
    "update":""
  },
"Han5-kok":{
    "text":" | 韩国 | ",
    "romazi":"",
    "hanzis":"韩国",
    "hanzit":"",
    "variant":"",
    "etymology":"",
    "partOfSpeech":"",
    "types":"",
    "definition":[""],
    "example":[""],
    "note":"",
    "update":""
  },
"hang5":{
    "text":" | 行 | ",
    "romazi":"",
    "hanzis":"行",
    "hanzit":"",
    "variant":"",
    "etymology":"",
    "partOfSpeech":"",
    "types":"",
    "definition":[""],
    "example":[""],
    "note":"",
    "update":""
  },
"hang5-pan1":{
    "text":" | 航班 | ",
    "romazi":"",
    "hanzis":"航班",
    "hanzit":"",
    "variant":"",
    "etymology":"",
    "partOfSpeech":"",
    "types":"",
    "definition":[""],
    "example":[""],
    "note":"",
    "update":""
  },
"Hang5-tsiu1":{
    "text":" | 杭州 | ",
    "romazi":"",
    "hanzis":"杭州",
    "hanzit":"",
    "variant":"",
    "etymology":"",
    "partOfSpeech":"",
    "types":"",
    "definition":[""],
    "example":[""],
    "note":"",
    "update":""
  },
"hai6":{
    "text":" | 亥 | ",
    "romazi":"",
    "hanzis":"亥",
    "hanzit":"",
    "variant":"",
    "etymology":"",
    "partOfSpeech":"",
    "types":"",
    "definition":[""],
    "example":[""],
    "note":"",
    "update":""
  },
"hai7":{
    "text":" | 害 | ",
    "romazi":"",
    "hanzis":"害",
    "hanzit":"",
    "variant":"",
    "etymology":"",
    "partOfSpeech":"",
    "types":"",
    "definition":[""],
    "example":[""],
    "note":"",
    "update":""
  },
"hau5-bi2":{
    "text":" | 毫米 | ",
    "romazi":"",
    "hanzis":"毫米",
    "hanzit":"",
    "variant":"",
    "etymology":"",
    "partOfSpeech":"",
    "types":"",
    "definition":[""],
    "example":[""],
    "note":"",
    "update":""
  },
"hau6-ser1":{
    "text":" | 后生 | ",
    "romazi":"",
    "hanzis":"后生",
    "hanzit":"",
    "variant":"",
    "etymology":"",
    "partOfSpeech":"",
    "types":"",
    "definition":[""],
    "example":[""],
    "note":"",
    "update":""
  },
"hau6-ser1-kya2":{
    "text":" | 后生囝 | ",
    "romazi":"",
    "hanzis":"后生囝",
    "hanzit":"",
    "variant":"",
    "etymology":"",
    "partOfSpeech":"",
    "types":"",
    "definition":[""],
    "example":[""],
    "note":"",
    "update":""
  },
"hau7-kue2":{
    "text":" | 效果 | ",
    "romazi":"",
    "hanzis":"效果",
    "hanzit":"",
    "variant":"",
    "etymology":"",
    "partOfSpeech":"",
    "types":"",
    "definition":[""],
    "example":[""],
    "note":"",
    "update":""
  },
"haw3":{
    "text":" | 好 | ",
    "romazi":"",
    "hanzis":"好",
    "hanzit":"",
    "variant":"",
    "etymology":"",
    "partOfSpeech":"",
    "types":"",
    "definition":[""],
    "example":[""],
    "note":"",
    "update":""
  },
"ho2":{
    "text":" | 好 | ",
    "romazi":"",
    "hanzis":"好",
    "hanzit":"",
    "variant":"",
    "etymology":"",
    "partOfSpeech":"",
    "types":"",
    "definition":[""],
    "example":[""],
    "note":"",
    "update":""
  },
"hoh":{
    "text":" |  | ",
    "romazi":"",
    "hanzis":"",
    "hanzit":"",
    "variant":"",
    "etymology":"",
    "partOfSpeech":"",
    "types":"",
    "definition":[""],
    "example":[""],
    "note":"",
    "update":""
  },
"ho7-be2":{
    "text":" | 号码 | ",
    "romazi":"",
    "hanzis":"号码",
    "hanzit":"",
    "variant":"",
    "etymology":"",
    "partOfSpeech":"",
    "types":"",
    "definition":[""],
    "example":[""],
    "note":"",
    "update":""
  },
"hox":{
    "text":" | 鹤 | ",
    "romazi":"",
    "hanzis":"鹤",
    "hanzit":"",
    "variant":"",
    "etymology":"",
    "partOfSpeech":"",
    "types":"",
    "definition":[""],
    "example":[""],
    "note":"",
    "update":""
  },
"hor":{
    "text":" |  | ",
    "romazi":"",
    "hanzis":"",
    "hanzit":"",
    "variant":"",
    "etymology":"",
    "partOfSpeech":"",
    "types":"",
    "definition":[""],
    "example":[""],
    "note":"",
    "update":""
  },
"hong6-huang5":{
    "text":" | 凤凰 | ",
    "romazi":"",
    "hanzis":"凤凰",
    "hanzit":"",
    "variant":"",
    "etymology":"",
    "partOfSpeech":"",
    "types":"",
    "definition":[""],
    "example":[""],
    "note":"",
    "update":""
  },
"hog-tsuang1":{
    "text":" | 服装 | ",
    "romazi":"",
    "hanzis":"服装",
    "hanzit":"",
    "variant":"",
    "etymology":"",
    "partOfSpeech":"",
    "types":"",
    "definition":[""],
    "example":[""],
    "note":"",
    "update":""
  },
"hoi6":{
    "text":" | 蟹 | ",
    "romazi":"",
    "hanzis":"蟹",
    "hanzit":"",
    "variant":"",
    "etymology":"",
    "partOfSpeech":"",
    "types":"",
    "definition":[""],
    "example":[""],
    "note":"",
    "update":""
  },
"hou5":{
    "text":" | 胡 | ",
    "romazi":"",
    "hanzis":"胡",
    "hanzit":"",
    "variant":"",
    "etymology":"",
    "partOfSpeech":"",
    "types":"",
    "definition":[""],
    "example":[""],
    "note":"",
    "update":""
  },
"hou5-lou5":{
    "text":" | 葫芦 | ",
    "romazi":"",
    "hanzis":"葫芦",
    "hanzit":"",
    "variant":"",
    "etymology":"",
    "partOfSpeech":"",
    "types":"",
    "definition":[""],
    "example":[""],
    "note":"",
    "update":""
  },
"hou6":{
    "text":" | 雨 | ",
    "romazi":"",
    "hanzis":"雨",
    "hanzit":"",
    "variant":"",
    "etymology":"",
    "partOfSpeech":"",
    "types":"",
    "definition":[""],
    "example":[""],
    "note":"",
    "update":""
  },
"hou6-tsia1":{
    "text":" | 雨遮 | ",
    "romazi":"",
    "hanzis":"雨遮",
    "hanzit":"",
    "variant":"",
    "etymology":"",
    "partOfSpeech":"",
    "types":"",
    "definition":[""],
    "example":[""],
    "note":"",
    "update":""
  },
"hou6-tsia6":{
    "text":" | 户籍 | ",
    "romazi":"",
    "hanzis":"户籍",
    "hanzit":"",
    "variant":"",
    "etymology":"",
    "partOfSpeech":"",
    "types":"",
    "definition":[""],
    "example":[""],
    "note":"",
    "update":""
  },
"how2":{
    "text":" | 虎 | ",
    "romazi":"",
    "hanzis":"虎",
    "hanzit":"",
    "variant":"",
    "etymology":"",
    "partOfSpeech":"",
    "types":"",
    "definition":[""],
    "example":[""],
    "note":"",
    "update":""
  },
"he1":{
    "text":" |  | ",
    "romazi":"",
    "hanzis":"",
    "hanzit":"",
    "variant":"",
    "etymology":"",
    "partOfSpeech":"",
    "types":"",
    "definition":[""],
    "example":[""],
    "note":"累",
    "update":""
  },
"heh":{
    "text":" | 吓 | ",
    "romazi":"",
    "hanzis":"吓",
    "hanzit":"",
    "variant":"",
    "etymology":"",
    "partOfSpeech":"",
    "types":"",
    "definition":[""],
    "example":[""],
    "note":"",
    "update":""
  },
"he5":{
    "text":" | 虾 | ",
    "romazi":"",
    "hanzis":"虾",
    "hanzit":"",
    "variant":"",
    "etymology":"",
    "partOfSpeech":"",
    "types":"",
    "definition":[""],
    "example":[""],
    "note":"",
    "update":""
  },
"he7":{
    "text":" | 夏 | ",
    "romazi":"",
    "hanzis":"夏",
    "hanzit":"",
    "variant":"",
    "etymology":"",
    "partOfSpeech":"",
    "types":"",
    "definition":[""],
    "example":[""],
    "note":"",
    "update":""
  },
"herx":{
    "text":" |  | ",
    "romazi":"",
    "hanzis":"",
    "hanzit":"",
    "variant":"",
    "etymology":"",
    "partOfSpeech":"",
    "types":"",
    "definition":[""],
    "example":[""],
    "note":"",
    "update":""
  },
"heng1":{
    "text":" | 兴 | ",
    "romazi":"",
    "hanzis":"兴",
    "hanzit":"",
    "variant":"",
    "etymology":"",
    "partOfSpeech":"",
    "types":"",
    "definition":[""],
    "example":[""],
    "note":"",
    "update":""
  },
"heng3-hun3":{
    "text":" | 兴奋 | ",
    "romazi":"",
    "hanzis":"兴奋",
    "hanzit":"",
    "variant":"",
    "etymology":"",
    "partOfSpeech":"",
    "types":"",
    "definition":[""],
    "example":[""],
    "note":"",
    "update":""
  },
"hek-pan2":{
    "text":" | 黑板 | ",
    "romazi":"",
    "hanzis":"黑板",
    "hanzit":"",
    "variant":"",
    "etymology":"",
    "partOfSpeech":"",
    "types":"",
    "definition":[""],
    "example":[""],
    "note":"",
    "update":""
  },
"Heng5":{
    "text":" | 王 | ",
    "romazi":"",
    "hanzis":"王",
    "hanzit":"",
    "variant":"",
    "etymology":"",
    "partOfSpeech":"",
    "types":"",
    "definition":[""],
    "example":[""],
    "note":"",
    "update":""
  },
"heng5-tsuang6":{
    "text":" | 形状 | ",
    "romazi":"",
    "hanzis":"形状",
    "hanzit":"",
    "variant":"",
    "etymology":"",
    "partOfSpeech":"",
    "types":"",
    "definition":[""],
    "example":[""],
    "note":"",
    "update":""
  },
"heg":{
    "text":" | 乏 | ",
    "romazi":"",
    "hanzis":"乏",
    "hanzit":"",
    "variant":"",
    "etymology":"",
    "partOfSpeech":"",
    "types":"",
    "definition":[""],
    "example":[""],
    "note":"",
    "update":""
  },
"hi1-mo7":{
    "text":" | 希望 | ",
    "romazi":"",
    "hanzis":"希望",
    "hanzit":"",
    "variant":"",
    "etymology":"",
    "partOfSpeech":"",
    "types":"",
    "definition":[""],
    "example":[""],
    "note":"",
    "update":""
  },
"hi3":{
    "text":" | 戏 | ",
    "romazi":"",
    "hanzis":"戏",
    "hanzit":"",
    "variant":"",
    "etymology":"",
    "partOfSpeech":"",
    "types":"",
    "definition":[""],
    "example":[""],
    "note":"",
    "update":""
  },
"hi6-liad":{
    "text":" | 系列 | ",
    "romazi":"",
    "hanzis":"系列",
    "hanzit":"",
    "variant":"",
    "etymology":"",
    "partOfSpeech":"",
    "types":"",
    "definition":[""],
    "example":[""],
    "note":"",
    "update":""
  },
"hyi5":{
    "text":" | 弦 | ",
    "romazi":"",
    "hanzis":"弦",
    "hanzit":"",
    "variant":"",
    "etymology":"",
    "partOfSpeech":"",
    "types":"",
    "definition":[""],
    "example":[""],
    "note":"",
    "update":""
  },
"hyi6":{
    "text":" | 耳 | ",
    "romazi":"",
    "hanzis":"耳",
    "hanzit":"",
    "variant":"",
    "etymology":"",
    "partOfSpeech":"",
    "types":"",
    "definition":[""],
    "example":[""],
    "note":"",
    "update":""
  },
"him5":{
    "text":" | 熊 | ",
    "romazi":"",
    "hanzis":"熊",
    "hanzit":"",
    "variant":"",
    "etymology":"",
    "partOfSpeech":"",
    "types":"",
    "definition":[""],
    "example":[""],
    "note":"",
    "update":""
  },
"hin7":{
    "text":" |  | ",
    "romazi":"",
    "hanzis":"",
    "hanzit":"",
    "variant":"",
    "etymology":"",
    "partOfSpeech":"",
    "types":"",
    "definition":[""],
    "example":[""],
    "note":"",
    "update":""
  },
"hia1":{
    "text":" | 靴 | ",
    "romazi":"",
    "hanzis":"靴",
    "hanzit":"",
    "variant":"",
    "etymology":"",
    "partOfSpeech":"",
    "types":"",
    "definition":[""],
    "example":[""],
    "note":"",
    "update":""
  },
"hia2":{
    "text":" |  | ",
    "romazi":"",
    "hanzis":"",
    "hanzit":"",
    "variant":"",
    "etymology":"",
    "partOfSpeech":"",
    "types":"",
    "definition":[""],
    "example":[""],
    "note":"",
    "update":""
  },
"hiah":{
    "text":" | 歇 | ",
    "romazi":"",
    "hanzis":"歇",
    "hanzit":"",
    "variant":"",
    "etymology":"",
    "partOfSpeech":"",
    "types":"",
    "definition":[""],
    "example":[""],
    "note":"",
    "update":""
  },
"hya1":{
    "text":" | 兄 | ",
    "romazi":"",
    "hanzis":"兄",
    "hanzit":"",
    "variant":"",
    "etymology":"",
    "partOfSpeech":"",
    "types":"",
    "definition":[""],
    "example":[""],
    "note":"",
    "update":""
  },
"hya5":{
    "text":" | 燃 | ",
    "romazi":"",
    "hanzis":"燃",
    "hanzit":"",
    "variant":"",
    "etymology":"",
    "partOfSpeech":"",
    "types":"",
    "definition":[""],
    "example":[""],
    "note":"",
    "update":""
  },
"hiam1":{
    "text":" | 莶 | ",
    "romazi":"",
    "hanzis":"莶",
    "hanzit":"",
    "variant":"",
    "etymology":"",
    "partOfSpeech":"",
    "types":"",
    "definition":[""],
    "example":[""],
    "note":"",
    "update":""
  },
"hiam1-tsie1":{
    "text":" | 莶椒 | ",
    "romazi":"",
    "hanzis":"莶椒",
    "hanzit":"",
    "variant":"",
    "etymology":"",
    "partOfSpeech":"",
    "types":"",
    "definition":[""],
    "example":[""],
    "note":"",
    "update":""
  },
"hiam2":{
    "text":" | 险 | ",
    "romazi":"",
    "hanzis":"险",
    "hanzit":"",
    "variant":"",
    "etymology":"",
    "partOfSpeech":"",
    "types":"",
    "definition":[""],
    "example":[""],
    "note":"",
    "update":""
  },
"hiam5":{
    "text":" | 嫌 | ",
    "romazi":"",
    "hanzis":"嫌",
    "hanzit":"",
    "variant":"",
    "etymology":"",
    "partOfSpeech":"",
    "types":"",
    "definition":[""],
    "example":[""],
    "note":"",
    "update":""
  },
"hiap-tso6":{
    "text":" | 协助 | ",
    "romazi":"",
    "hanzis":"协助",
    "hanzit":"",
    "variant":"",
    "etymology":"",
    "partOfSpeech":"",
    "types":"",
    "definition":[""],
    "example":[""],
    "note":"",
    "update":""
  },
"hian2-si7":{
    "text":" | 显示 | ",
    "romazi":"",
    "hanzis":"显示",
    "hanzit":"",
    "variant":"",
    "etymology":"",
    "partOfSpeech":"",
    "types":"",
    "definition":[""],
    "example":[""],
    "note":"",
    "update":""
  },
"hian3-hueh":{
    "text":" | 献血 | ",
    "romazi":"",
    "hanzis":"献血",
    "hanzit":"",
    "variant":"",
    "etymology":"",
    "partOfSpeech":"",
    "types":"",
    "definition":[""],
    "example":[""],
    "note":"",
    "update":""
  },
"hiang2":{
    "text":" | 响 | ",
    "romazi":"",
    "hanzis":"响",
    "hanzit":"",
    "variant":"",
    "etymology":"",
    "partOfSpeech":"",
    "types":"",
    "definition":[""],
    "example":[""],
    "note":"",
    "update":""
  },
"hiang2-siu6":{
    "text":" | 享受 | ",
    "romazi":"",
    "hanzis":"享受",
    "hanzit":"",
    "variant":"",
    "etymology":"",
    "partOfSpeech":"",
    "types":"",
    "definition":[""],
    "example":[""],
    "note":"",
    "update":""
  },
"hiau2":{
    "text":" | 晓 | ",
    "romazi":"",
    "hanzis":"晓",
    "hanzit":"",
    "variant":"",
    "etymology":"",
    "partOfSpeech":"",
    "types":"",
    "definition":[""],
    "example":[""],
    "note":"",
    "update":""
  },
"hiau2":{
    "text":" |  | ",
    "romazi":"",
    "hanzis":"",
    "hanzit":"",
    "variant":"",
    "etymology":"",
    "partOfSpeech":"",
    "types":"",
    "definition":[""],
    "example":[""],
    "note":"",
    "update":""
  },
"hiong1":{
    "text":" | 凶 | ",
    "romazi":"",
    "hanzis":"凶",
    "hanzit":"",
    "variant":"",
    "etymology":"",
    "partOfSpeech":"",
    "types":"",
    "definition":[""],
    "example":[""],
    "note":"",
    "update":""
  },
"hiong5":{
    "text":" | 雄 | ",
    "romazi":"",
    "hanzis":"雄",
    "hanzit":"",
    "variant":"",
    "etymology":"",
    "partOfSpeech":"",
    "types":"",
    "definition":[""],
    "example":[""],
    "note":"",
    "update":""
  },
"hiang1":{
    "text":" | 香 | ",
    "romazi":"",
    "hanzis":"香",
    "hanzit":"",
    "variant":"",
    "etymology":"",
    "partOfSpeech":"",
    "types":"",
    "definition":[""],
    "example":[""],
    "note":"",
    "update":""
  },
"hye1-li2":{
    "text":" | 乡里 | ",
    "romazi":"",
    "hanzis":"乡里",
    "hanzit":"",
    "variant":"",
    "etymology":"",
    "partOfSpeech":"",
    "types":"",
    "definition":[""],
    "example":[""],
    "note":"",
    "update":""
  },
"hyu1":{
    "text":" |  | ",
    "romazi":"",
    "hanzis":"",
    "hanzit":"",
    "variant":"",
    "etymology":"",
    "partOfSpeech":"",
    "types":"",
    "definition":[""],
    "example":[""],
    "note":"掀开",
    "update":""
  },
"hu2":{
    "text":" |  | ",
    "romazi":"",
    "hanzis":"",
    "hanzit":"",
    "variant":"",
    "etymology":"",
    "partOfSpeech":"",
    "types":"",
    "definition":[""],
    "example":[""],
    "note":"糊弄",
    "update":""
  },
"hu3":{
    "text":" | 赴 | ",
    "romazi":"",
    "hanzis":"赴",
    "hanzit":"",
    "variant":"",
    "etymology":"",
    "partOfSpeech":"",
    "types":"",
    "definition":[""],
    "example":[""],
    "note":"",
    "update":""
  },
"hu5":{
    "text":" | 壶 | ",
    "romazi":"",
    "hanzis":"壶",
    "hanzit":"",
    "variant":"",
    "etymology":"",
    "partOfSpeech":"",
    "types":"",
    "definition":[""],
    "example":[""],
    "note":"",
    "update":""
  },
"hu5":{
    "text":" | 扶 | ",
    "romazi":"",
    "hanzis":"扶",
    "hanzit":"",
    "variant":"",
    "etymology":"",
    "partOfSpeech":"",
    "types":"",
    "definition":[""],
    "example":[""],
    "note":"",
    "update":""
  },
"hu5-hax":{
    "text":" | 符合 | ",
    "romazi":"",
    "hanzis":"符合",
    "hanzit":"",
    "variant":"",
    "etymology":"",
    "partOfSpeech":"",
    "types":"",
    "definition":[""],
    "example":[""],
    "note":"",
    "update":""
  },
"hu6-tso6":{
    "text":" | 辅助 | ",
    "romazi":"",
    "hanzis":"辅助",
    "hanzit":"",
    "variant":"",
    "etymology":"",
    "partOfSpeech":"",
    "types":"",
    "definition":[""],
    "example":[""],
    "note":"",
    "update":""
  },
"hun1":{
    "text":" | 分 | ",
    "romazi":"",
    "hanzis":"分",
    "hanzit":"",
    "variant":"",
    "etymology":"",
    "partOfSpeech":"",
    "types":"",
    "definition":[""],
    "example":[""],
    "note":"",
    "update":""
  },
"hun1":{
    "text":" | 熏 | ",
    "romazi":"",
    "hanzis":"熏",
    "hanzit":"",
    "variant":"",
    "etymology":"",
    "partOfSpeech":"",
    "types":"",
    "definition":[""],
    "example":[""],
    "note":"",
    "update":""
  },
"hun2":{
    "text":" | 粉 | ",
    "romazi":"",
    "hanzis":"粉",
    "hanzit":"",
    "variant":"",
    "etymology":"",
    "partOfSpeech":"",
    "types":"",
    "definition":[""],
    "example":[""],
    "note":"",
    "update":""
  },
"hun3-lian7":{
    "text":" | 训练 | ",
    "romazi":"",
    "hanzis":"训练",
    "hanzit":"",
    "variant":"",
    "etymology":"",
    "partOfSpeech":"",
    "types":"",
    "definition":[""],
    "example":[""],
    "note":"",
    "update":""
  },
"hun5":{
    "text":" | 云 | ",
    "romazi":"",
    "hanzis":"云",
    "hanzit":"",
    "variant":"",
    "etymology":"",
    "partOfSpeech":"",
    "types":"",
    "definition":[""],
    "example":[""],
    "note":"",
    "update":""
  },
"hun6-luan6":{
    "text":" | 混乱 | ",
    "romazi":"",
    "hanzis":"混乱",
    "hanzit":"",
    "variant":"",
    "etymology":"",
    "partOfSpeech":"",
    "types":"",
    "definition":[""],
    "example":[""],
    "note":"",
    "update":""
  },
"hud":{
    "text":" | 核 | ",
    "romazi":"",
    "hanzis":"核",
    "hanzit":"",
    "variant":"",
    "etymology":"",
    "partOfSpeech":"",
    "types":"",
    "definition":[""],
    "example":[""],
    "note":"",
    "update":""
  },
"hud-tsou2":{
    "text":" | 佛祖 | ",
    "romazi":"",
    "hanzis":"佛祖",
    "hanzit":"",
    "variant":"",
    "etymology":"",
    "partOfSpeech":"",
    "types":"",
    "definition":[""],
    "example":[""],
    "note":"",
    "update":""
  },
"huah":{
    "text":" | 喝 | ",
    "romazi":"",
    "hanzis":"喝",
    "hanzit":"",
    "variant":"",
    "etymology":"",
    "partOfSpeech":"",
    "types":"",
    "definition":[""],
    "example":[""],
    "note":"",
    "update":""
  },
"hwa1":{
    "text":" | 还 | ",
    "romazi":"",
    "hanzis":"还",
    "hanzit":"",
    "variant":"",
    "etymology":"",
    "partOfSpeech":"",
    "types":"",
    "definition":[""],
    "example":[""],
    "note":"",
    "update":""
  },
"hwa1-hyi2":{
    "text":" | 欢喜 | ",
    "romazi":"",
    "hanzis":"欢喜",
    "hanzit":"",
    "variant":"",
    "etymology":"",
    "partOfSpeech":"",
    "types":"",
    "definition":[""],
    "example":[""],
    "note":"",
    "update":""
  },
"hwa5":{
    "text":" | 鼾 | ",
    "romazi":"",
    "hanzis":"鼾",
    "hanzit":"",
    "variant":"",
    "etymology":"",
    "partOfSpeech":"",
    "types":"",
    "definition":[""],
    "example":[""],
    "note":"",
    "update":""
  },
"huap-lud":{
    "text":" | 法律 | ",
    "romazi":"",
    "hanzis":"法律",
    "hanzit":"",
    "variant":"",
    "etymology":"",
    "partOfSpeech":"",
    "types":"",
    "definition":[""],
    "example":[""],
    "note":"",
    "update":""
  },
"huam5-zin5":{
    "text":" | 凡人 | ",
    "romazi":"",
    "hanzis":"凡人",
    "hanzit":"",
    "variant":"",
    "etymology":"",
    "partOfSpeech":"",
    "types":"",
    "definition":[""],
    "example":[""],
    "note":"",
    "update":""
  },
"huam6-tsia2":{
    "text":" | 患者 | ",
    "romazi":"",
    "hanzis":"患者",
    "hanzit":"",
    "variant":"",
    "etymology":"",
    "partOfSpeech":"",
    "types":"",
    "definition":[""],
    "example":[""],
    "note":"",
    "update":""
  },
"huam6-huap":{
    "text":" | 犯法 | ",
    "romazi":"",
    "hanzis":"犯法",
    "hanzit":"",
    "variant":"",
    "etymology":"",
    "partOfSpeech":"",
    "types":"",
    "definition":[""],
    "example":[""],
    "note":"",
    "update":""
  },
"huan1-qeh":{
    "text":" | 番客 | ",
    "romazi":"",
    "hanzis":"番客",
    "hanzit":"",
    "variant":"",
    "etymology":"",
    "partOfSpeech":"",
    "types":"",
    "definition":[""],
    "example":[""],
    "note":"",
    "update":""
  },
"huat":{
    "text":" | 发 | ",
    "romazi":"",
    "hanzis":"发",
    "hanzit":"",
    "variant":"",
    "etymology":"",
    "partOfSpeech":"",
    "types":"",
    "definition":[""],
    "example":[""],
    "note":"",
    "update":""
  },
"huam5-lo2":{
    "text":" | 烦恼 | ",
    "romazi":"",
    "hanzis":"烦恼",
    "hanzit":"",
    "variant":"",
    "etymology":"",
    "partOfSpeech":"",
    "types":"",
    "definition":[""],
    "example":[""],
    "note":"",
    "update":""
  },
"huam5-nau2":{
    "text":" | 烦恼 | ",
    "romazi":"",
    "hanzis":"烦恼",
    "hanzit":"",
    "variant":"",
    "etymology":"",
    "partOfSpeech":"",
    "types":"",
    "definition":[""],
    "example":[""],
    "note":"",
    "update":""
  },
"huad":{
    "text":" | 罚 | ",
    "romazi":"",
    "hanzis":"罚",
    "hanzit":"",
    "variant":"",
    "etymology":"",
    "partOfSpeech":"",
    "types":"",
    "definition":[""],
    "example":[""],
    "note":"",
    "update":""
  },
"huad-quan2":{
    "text":" | 罚款 | ",
    "romazi":"",
    "hanzis":"罚款",
    "hanzit":"",
    "variant":"",
    "etymology":"",
    "partOfSpeech":"",
    "types":"",
    "definition":[""],
    "example":[""],
    "note":"",
    "update":""
  },
"huang1":{
    "text":" | 风 | ",
    "romazi":"",
    "hanzis":"风",
    "hanzit":"",
    "variant":"",
    "etymology":"",
    "partOfSpeech":"",
    "types":"",
    "definition":[""],
    "example":[""],
    "note":"",
    "update":""
  },
"huang1-min7":{
    "text":" | 方面 | ",
    "romazi":"",
    "hanzis":"方面",
    "hanzit":"",
    "variant":"",
    "etymology":"",
    "partOfSpeech":"",
    "types":"",
    "definition":[""],
    "example":[""],
    "note":"",
    "update":""
  },
"huang2-mun7":{
    "text":" | 访问 | ",
    "romazi":"",
    "hanzis":"访问",
    "hanzit":"",
    "variant":"",
    "etymology":"",
    "partOfSpeech":"",
    "types":"",
    "definition":[""],
    "example":[""],
    "note":"",
    "update":""
  },
"huang5-siu2":{
    "text":" | 防守 | ",
    "romazi":"",
    "hanzis":"防守",
    "hanzit":"",
    "variant":"",
    "etymology":"",
    "partOfSpeech":"",
    "types":"",
    "definition":[""],
    "example":[""],
    "note":"",
    "update":""
  },
"hue1":{
    "text":" | 花 | ",
    "romazi":"",
    "hanzis":"花",
    "hanzit":"",
    "variant":"",
    "etymology":"",
    "partOfSpeech":"",
    "types":"",
    "definition":[""],
    "example":[""],
    "note":"",
    "update":""
  },
"hue2":{
    "text":" | 火 | ",
    "romazi":"",
    "hanzis":"火",
    "hanzit":"",
    "variant":"",
    "etymology":"",
    "partOfSpeech":"",
    "types":"",
    "definition":[""],
    "example":[""],
    "note":"",
    "update":""
  },
"hueh":{
    "text":" | 血 | ",
    "romazi":"",
    "hanzis":"血",
    "hanzit":"",
    "variant":"",
    "etymology":"",
    "partOfSpeech":"",
    "types":"",
    "definition":[""],
    "example":[""],
    "note":"",
    "update":""
  },
"hue5":{
    "text":" | 回 | ",
    "romazi":"",
    "hanzis":"回",
    "hanzit":"",
    "variant":"",
    "etymology":"",
    "partOfSpeech":"",
    "types":"",
    "definition":[""],
    "example":[""],
    "note":"",
    "update":""
  },
"hwe5":{
    "text":" | 横 | ",
    "romazi":"",
    "hanzis":"横",
    "hanzit":"",
    "variant":"",
    "etymology":"",
    "partOfSpeech":"",
    "types":"",
    "definition":[""],
    "example":[""],
    "note":"",
    "update":""
  },
"hui-sye5":{
    "text":" | 非常 | ",
    "romazi":"",
    "hanzis":"非常",
    "hanzit":"",
    "variant":"",
    "etymology":"",
    "partOfSpeech":"",
    "types":"",
    "definition":[""],
    "example":[""],
    "note":"",
    "update":""
  },
"hui3":{
    "text":" | 肺 | ",
    "romazi":"",
    "hanzis":"肺",
    "hanzit":"",
    "variant":"",
    "etymology":"",
    "partOfSpeech":"",
    "types":"",
    "definition":[""],
    "example":[""],
    "note":"",
    "update":""
  },
"hui3-muex":{
    "text":" | 废物 | ",
    "romazi":"",
    "hanzis":"废物",
    "hanzit":"",
    "variant":"",
    "etymology":"",
    "partOfSpeech":"",
    "types":"",
    "definition":[""],
    "example":[""],
    "note":"",
    "update":""
  },
"hir1":{
    "text":" | 虚 | ",
    "romazi":"",
    "hanzis":"虚",
    "hanzit":"",
    "variant":"",
    "etymology":"",
    "partOfSpeech":"",
    "types":"",
    "definition":[""],
    "example":[""],
    "note":"",
    "update":""
  },
"hir2":{
    "text":" | 彼 | ",
    "romazi":"",
    "hanzis":"彼",
    "hanzit":"",
    "variant":"",
    "etymology":"",
    "partOfSpeech":"",
    "types":"",
    "definition":[""],
    "example":[""],
    "note":"",
    "update":""
  },
"hir5":{
    "text":" | 鱼 | ",
    "romazi":"",
    "hanzis":"鱼",
    "hanzit":"",
    "variant":"",
    "etymology":"",
    "partOfSpeech":"",
    "types":"",
    "definition":[""],
    "example":[""],
    "note":"",
    "update":""
  },
"hirn1-sye2":{
    "text":" | 欣赏 | ",
    "romazi":"",
    "hanzis":"欣赏",
    "hanzit":"",
    "variant":"",
    "etymology":"",
    "partOfSpeech":"",
    "types":"",
    "definition":[""],
    "example":[""],
    "note":"",
    "update":""
  },
"hng6":{
    "text":" | 远 | ",
    "romazi":"",
    "hanzis":"远",
    "hanzit":"",
    "variant":"",
    "etymology":"",
    "partOfSpeech":"",
    "types":"",
    "definition":[""],
    "example":[""],
    "note":"",
    "update":""
  }

}